{
    "name": "一二第2弹",
    "type": "image",
    "items": [
        {
            "key": "onetwo-42",
            "val": "https://emotion.sky123.top/onetwo/data/42.gif"
        },
        {
            "key": "onetwo-43",
            "val": "https://emotion.sky123.top/onetwo/data/43.gif"
        },
        {
            "key": "onetwo-44",
            "val": "https://emotion.sky123.top/onetwo/data/44.gif"
        },
        {
            "key": "onetwo-45",
            "val": "https://emotion.sky123.top/onetwo/data/45.gif"
        },
        {
            "key": "onetwo-46",
            "val": "https://emotion.sky123.top/onetwo/data/46.gif"
        },
        {
            "key": "onetwo-47",
            "val": "https://emotion.sky123.top/onetwo/data/47.gif"
        },
        {
            "key": "onetwo-48",
            "val": "https://emotion.sky123.top/onetwo/data/48.gif"
        },
        {
            "key": "onetwo-49",
            "val": "https://emotion.sky123.top/onetwo/data/49.gif"
        },
        {
            "key": "onetwo-50",
            "val": "https://emotion.sky123.top/onetwo/data/50.gif"
        },
        {
            "key": "onetwo-51",
            "val": "https://emotion.sky123.top/onetwo/data/51.gif"
        },
        {
            "key": "onetwo-52",
            "val": "https://emotion.sky123.top/onetwo/data/52.gif"
        },
        {
            "key": "onetwo-53",
            "val": "https://emotion.sky123.top/onetwo/data/53.gif"
        },
        {
            "key": "onetwo-54",
            "val": "https://emotion.sky123.top/onetwo/data/54.gif"
        },
        {
            "key": "onetwo-55",
            "val": "https://emotion.sky123.top/onetwo/data/55.gif"
        },
        {
            "key": "onetwo-56",
            "val": "https://emotion.sky123.top/onetwo/data/56.gif"
        },
        {
            "key": "onetwo-57",
            "val": "https://emotion.sky123.top/onetwo/data/57.gif"
        },
        {
            "key": "onetwo-58",
            "val": "https://emotion.sky123.top/onetwo/data/58.gif"
        },
        {
            "key": "onetwo-59",
            "val": "https://emotion.sky123.top/onetwo/data/59.gif"
        },
        {
            "key": "onetwo-60",
            "val": "https://emotion.sky123.top/onetwo/data/60.gif"
        },
        {
            "key": "onetwo-61",
            "val": "https://emotion.sky123.top/onetwo/data/61.gif"
        },
        {
            "key": "onetwo-62",
            "val": "https://emotion.sky123.top/onetwo/data/62.gif"
        },
        {
            "key": "onetwo-63",
            "val": "https://emotion.sky123.top/onetwo/data/63.gif"
        },
        {
            "key": "onetwo-64",
            "val": "https://emotion.sky123.top/onetwo/data/64.gif"
        },
        {
            "key": "onetwo-65",
            "val": "https://emotion.sky123.top/onetwo/data/65.gif"
        },
        {
            "key": "onetwo-66",
            "val": "https://emotion.sky123.top/onetwo/data/66.gif"
        },
        {
            "key": "onetwo-67",
            "val": "https://emotion.sky123.top/onetwo/data/67.gif"
        },
        {
            "key": "onetwo-68",
            "val": "https://emotion.sky123.top/onetwo/data/68.gif"
        },
        {
            "key": "onetwo-69",
            "val": "https://emotion.sky123.top/onetwo/data/69.gif"
        },
        {
            "key": "onetwo-70",
            "val": "https://emotion.sky123.top/onetwo/data/70.gif"
        },
        {
            "key": "onetwo-71",
            "val": "https://emotion.sky123.top/onetwo/data/71.gif"
        },
        {
            "key": "onetwo-72",
            "val": "https://emotion.sky123.top/onetwo/data/72.gif"
        },
        {
            "key": "onetwo-73",
            "val": "https://emotion.sky123.top/onetwo/data/73.gif"
        },
        {
            "key": "onetwo-74",
            "val": "https://emotion.sky123.top/onetwo/data/74.gif"
        },
        {
            "key": "onetwo-75",
            "val": "https://emotion.sky123.top/onetwo/data/75.gif"
        },
        {
            "key": "onetwo-76",
            "val": "https://emotion.sky123.top/onetwo/data/76.gif"
        },
        {
            "key": "onetwo-77",
            "val": "https://emotion.sky123.top/onetwo/data/77.gif"
        },
        {
            "key": "onetwo-78",
            "val": "https://emotion.sky123.top/onetwo/data/78.gif"
        },
        {
            "key": "onetwo-79",
            "val": "https://emotion.sky123.top/onetwo/data/79.gif"
        },
        {
            "key": "onetwo-80",
            "val": "https://emotion.sky123.top/onetwo/data/80.gif"
        },
        {
            "key": "onetwo-81",
            "val": "https://emotion.sky123.top/onetwo/data/81.gif"
        },
        {
            "key": "onetwo-82",
            "val": "https://emotion.sky123.top/onetwo/data/82.gif"
        }
    ]
}